<?xml version="1.0"?>
<portlet-app xmlns="http://java.sun.com/xml/ns/portlet/portlet-app_2_0.xsd" xmlns:xsi="http://www.w3.org/2001/XMLSchema-instance" xsi:schemaLocation="http://java.sun.com/xml/ns/portlet/portlet-app_2_0.xsd http://java.sun.com/xml/ns/portlet/portlet-app_2_0.xsd" version="2.0">
	<portlet>
		<portlet-name>AddProducts</portlet-name>
		<display-name>AddProducts</display-name>
			<portlet-class>org.springframework.web.portlet.DispatcherPortlet</portlet-class>
		<init-param>
			<name>contextConfigLocation</name>
			<value>/WEB-INF/AddProducts-portlet.xml</value>
		</init-param>
		<supports>
			<mime-type>text/html</mime-type>
		</supports>
		<portlet-info>
			<title>AddProducts</title>
			<short-title>AddProducts</short-title>
			<keywords>AddProducts</keywords>
		</portlet-info>
		<security-role-ref>
			<role-name>administrator</role-name>
		</security-role-ref>
		<security-role-ref>
			<role-name>guest</role-name>
		</security-role-ref>
		<security-role-ref>
			<role-name>power-user</role-name>
		</security-role-ref>
		<security-role-ref>
			<role-name>user</role-name>
		</security-role-ref>
	</portlet>
	<portlet>
		<portlet-name>AddSuppliers</portlet-name>
		<display-name>Add Supplier</display-name>
		<portlet-class>org.springframework.web.portlet.DispatcherPortlet</portlet-class>
		<init-param>
			<name>contextConfigLocation</name>
			<value>/WEB-INF/AddSupplier-portlet.xml</value>
		</init-param>
		<supports>
			<mime-type>text/html</mime-type>
			<portlet-mode>view</portlet-mode>
		</supports>
		<portlet-info>
			<title>Add Supplier</title>
			<short-title>Add Supplier</short-title>
			<keywords></keywords>
		</portlet-info>
		<security-role-ref>
			<role-name>administrator</role-name>
		</security-role-ref>
		<security-role-ref>
			<role-name>guest</role-name>
		</security-role-ref>
		<security-role-ref>
			<role-name>power-user</role-name>
		</security-role-ref>
		<security-role-ref>
			<role-name>user</role-name>
		</security-role-ref>
	</portlet>
	<portlet>
		<portlet-name>EditProduct</portlet-name>
		<display-name>Edit Product</display-name>
		<portlet-class>org.springframework.web.portlet.DispatcherPortlet</portlet-class>
		<init-param>
			<name>contextConfigLocation</name>
			<value>/WEB-INF/EditProduct-portlet.xml</value>
		</init-param>
		<supports>
			<mime-type>text/html</mime-type>
			<portlet-mode>view</portlet-mode>
		</supports>
		<portlet-info>
			<title>Edit Product</title>
			<short-title>Edit Product</short-title>
			<keywords></keywords>
		</portlet-info>
		<security-role-ref>
			<role-name>administrator</role-name>
		</security-role-ref>
		<security-role-ref>
			<role-name>guest</role-name>
		</security-role-ref>
		<security-role-ref>
			<role-name>power-user</role-name>
		</security-role-ref>
		<security-role-ref>
			<role-name>user</role-name>
		</security-role-ref>
	</portlet>
	<portlet>
		<portlet-name>ProductCategory</portlet-name>
		<display-name>Product Category</display-name>
		<portlet-class>org.springframework.web.portlet.DispatcherPortlet</portlet-class>
		<init-param>
			<name>contextConfigLocation</name>
			<value>/WEB-INF/ProductCategory-portlet.xml</value>
		</init-param>
		<supports>
			<mime-type>text/html</mime-type>
			<portlet-mode>view</portlet-mode>
		</supports>
		<portlet-info>
			<title>Product Category</title>
			<short-title>Product Category</short-title>
			<keywords></keywords>
		</portlet-info>
		<security-role-ref>
			<role-name>administrator</role-name>
		</security-role-ref>
		<security-role-ref>
			<role-name>guest</role-name>
		</security-role-ref>
		<security-role-ref>
			<role-name>power-user</role-name>
		</security-role-ref>
		<security-role-ref>
			<role-name>user</role-name>
		</security-role-ref>
	</portlet>
	<portlet>
		<portlet-name>StockAdjustment</portlet-name>
		<display-name>Stock Adjustment</display-name>
		<portlet-class>org.springframework.web.portlet.DispatcherPortlet</portlet-class>
		<init-param>
			<name>contextConfigLocation</name>
			<value>/WEB-INF/StockAdjustment-portlet.xml</value>
		</init-param>
		<supports>
			<mime-type>text/html</mime-type>
			<portlet-mode>view</portlet-mode>
		</supports>
		<portlet-info>
			<title>Stock Adjustment</title>
			<short-title>Stock Adjustment</short-title>
			<keywords></keywords>
		</portlet-info>
		<security-role-ref>
			<role-name>administrator</role-name>
		</security-role-ref>
		<security-role-ref>
			<role-name>guest</role-name>
		</security-role-ref>
		<security-role-ref>
			<role-name>power-user</role-name>
		</security-role-ref>
		<security-role-ref>
			<role-name>user</role-name>
		</security-role-ref>
	</portlet>
	<portlet>
		<portlet-name>MrpAdjustment</portlet-name>
		<display-name>Mrp Adjustments</display-name>
		<portlet-class>org.springframework.web.portlet.DispatcherPortlet</portlet-class>
		<init-param>
			<name>contextConfigLocation</name>
			<value>/WEB-INF/MrpAdjustment-portlet.xml</value>
		</init-param>
		<supports>
			<mime-type>text/html</mime-type>
			<portlet-mode>view</portlet-mode>
		</supports>
		<portlet-info>
			<title>Mrp Adjustments</title>
			<short-title>Mrp Adjustments</short-title>
			<keywords></keywords>
		</portlet-info>
		<security-role-ref>
			<role-name>administrator</role-name>
		</security-role-ref>
		<security-role-ref>
			<role-name>guest</role-name>
		</security-role-ref>
		<security-role-ref>
			<role-name>power-user</role-name>
		</security-role-ref>
		<security-role-ref>
			<role-name>user</role-name>
		</security-role-ref>
	</portlet>
	<portlet>
		<portlet-name>SupplierPayment</portlet-name>
		<display-name>Supplier Payment</display-name>
		<portlet-class>org.springframework.web.portlet.DispatcherPortlet</portlet-class>
		<init-param>
			<name>contextConfigLocation</name>
			<value>/WEB-INF/SupplierPayment-portlet.xml</value>
		</init-param>
		<supports>
			<mime-type>text/html</mime-type>
			<portlet-mode>view</portlet-mode>
		</supports>
		<portlet-info>
			<title>Supplier Payment</title>
			<short-title>Supplier Payment</short-title>
			<keywords></keywords>
		</portlet-info>
		<security-role-ref>
			<role-name>administrator</role-name>
		</security-role-ref>
		<security-role-ref>
			<role-name>guest</role-name>
		</security-role-ref>
		<security-role-ref>
			<role-name>power-user</role-name>
		</security-role-ref>
		<security-role-ref>
			<role-name>user</role-name>
		</security-role-ref>
	</portlet>
	<portlet>
		<portlet-name>AlternateProduct</portlet-name>
		<display-name>Alternate Product</display-name>
		<portlet-class>org.springframework.web.portlet.DispatcherPortlet</portlet-class>
		<init-param>
			<name>contextConfigLocation</name>
			<value>/WEB-INF/AlternateProduct-portlet.xml</value>
		</init-param>
		<supports>
			<mime-type>text/html</mime-type>
			<portlet-mode>view</portlet-mode>
		</supports>
		<portlet-info>
			<title>Alternate Product</title>
			<short-title>Alternate Product</short-title>
			<keywords></keywords>
		</portlet-info>
		<security-role-ref>
			<role-name>administrator</role-name>
		</security-role-ref>
		<security-role-ref>
			<role-name>guest</role-name>
		</security-role-ref>
		<security-role-ref>
			<role-name>power-user</role-name>
		</security-role-ref>
		<security-role-ref>
			<role-name>user</role-name>
		</security-role-ref>
	</portlet>
	<portlet>
		<portlet-name>DiscountManagement</portlet-name>
		<display-name>Discount Management</display-name>
		<portlet-class>org.springframework.web.portlet.DispatcherPortlet</portlet-class>
		<init-param>
			<name>contextConfigLocation</name>
			<value>/WEB-INF/DiscountManagement-portlet.xml</value>
		</init-param>
		<supports>
			<mime-type>text/html</mime-type>
			<portlet-mode>view</portlet-mode>
		</supports>
		<portlet-info>
			<title>Discount Management</title>
			<short-title>Discount Management</short-title>
			<keywords></keywords>
		</portlet-info>
		<security-role-ref>
			<role-name>administrator</role-name>
		</security-role-ref>
		<security-role-ref>
			<role-name>guest</role-name>
		</security-role-ref>
		<security-role-ref>
			<role-name>power-user</role-name>
		</security-role-ref>
		<security-role-ref>
			<role-name>user</role-name>
		</security-role-ref>
	</portlet>
</portlet-app>